cwmaya/VERSION
cwmaya/__init__.py
cwmaya/coreweave.mod
cwmaya/post_install.py
cwmaya/helpers/__init__.py
cwmaya/helpers/conductor_helpers.py
cwmaya/helpers/const.py
cwmaya/helpers/desktop_app_helpers.py
cwmaya/helpers/layer_utils.py
cwmaya/helpers/node_utils.py
cwmaya/helpers/preset_helpers.py
cwmaya/helpers/reloader.py
cwmaya/helpers/spec_helpers.py
cwmaya/helpers/workflow_api_helpers.py
cwmaya/icons/conductor_logo_white.png
cwmaya/icons/cwAssSubmission.png
cwmaya/icons/cwChainSubmission.png
cwmaya/icons/cwSimRenderSubmission.png
cwmaya/icons/cwSmokeSubmission.png
cwmaya/icons/da_health_128x128.png
cwmaya/icons/out_cwAssSubmission.png
cwmaya/icons/out_cwChainSubmission.png
cwmaya/icons/out_cwSimRenderSubmission.png
cwmaya/icons/out_cwSmokeSubmission.png
cwmaya/icons/shelfIcons.psd
cwmaya/icons/tp_select_128x128.png
cwmaya/icons/wf_health_128x128.png
cwmaya/menus/__init__.py
cwmaya/menus/coreweave_menu.py
cwmaya/menus/tools_menu.py
cwmaya/plug-ins/CoreWeave.py
cwmaya/presets/cwChainSubmissionPreset_bambi.mel
cwmaya/presets/cwChainSubmissionPreset_bingo.mel
cwmaya/presets/cwChainSubmissionPreset_busywork.mel
cwmaya/presets/cwChainSubmissionPreset_default.mel
cwmaya/presets/cwChainSubmissionPreset_foobar.mel
cwmaya/presets/cwChainSubmissionPreset_hjk.mel
cwmaya/presets/cwSimRenderSubmissionPreset_default.mel
cwmaya/presets/cwSimRenderSubmissionPreset_defaut.mel
cwmaya/presets/cwSimRenderSubmissionPreset_demo.mel
cwmaya/presets/cwSimRenderSubmissionPreset_seven_frames.mel
cwmaya/presets/cwSimRenderSubmissionPreset_wip_maya_batch.mel
cwmaya/presets/cwSimRenderSubmissionPreset_with_dynattr.mel
cwmaya/presets/cwSmokeSubmissionPreset_default.mel
cwmaya/tabs/__init__.py
cwmaya/tabs/base_tab.py
cwmaya/tabs/comp_tab.py
cwmaya/tabs/export_tab.py
cwmaya/tabs/general_tab.py
cwmaya/tabs/job_tab.py
cwmaya/tabs/quicktime_tab.py
cwmaya/tabs/render_tab.py
cwmaya/tabs/script_task_tab.py
cwmaya/tabs/simple_tab.py
cwmaya/tabs/slack_tab.py
cwmaya/tabs/task_tab.py
cwmaya-0.0.1b29.dist-info/METADATA
cwmaya-0.0.1b29.dist-info/WHEEL
cwmaya-0.0.1b29.dist-info/top_level.txt
cwmaya-0.0.1b29.dist-info/RECORD
