Metadata-Version: 2.1
Name: cwmaya
Version: 0.0.1b29
Summary: Maya plugin for Conductor Cloud Rendering Platform.
Home-page: https://github.com/ConductorTechnologies/cwmaya
Author: coreweave
Author-email: info@conductortech.com
Classifier: Operating System :: OS Independent
Classifier: Programming Language :: Python
Classifier: Topic :: Multimedia :: Graphics :: 3D Rendering
Requires-Dist: pymel <2.0.0,>=1.4.0
Requires-Dist: cwstorm <1.0.0,>=0.6.3
Requires-Dist: requests <3.0.0,>=2.28.1
Requires-Dist: ciocore ==8.1.0-beta.4
Requires-Dist: ciopath <2.0.0,>=1.1.2
Requires-Dist: cioseq <1.0.0,>=0.5.1
Requires-Dist: psutil <6.0.0,>=5.8.0
Requires-Dist: pyperclip <2.0.0,>=1.9.0
